azure/mgmt/devhub/__init__.py
azure/mgmt/devhub/_configuration.py
azure/mgmt/devhub/_dev_hub_mgmt_client.py
azure/mgmt/devhub/_patch.py
azure/mgmt/devhub/_serialization.py
azure/mgmt/devhub/_vendor.py
azure/mgmt/devhub/_version.py
azure/mgmt/devhub/py.typed
azure/mgmt/devhub/aio/__init__.py
azure/mgmt/devhub/aio/_configuration.py
azure/mgmt/devhub/aio/_dev_hub_mgmt_client.py
azure/mgmt/devhub/aio/_patch.py
azure/mgmt/devhub/aio/_vendor.py
azure/mgmt/devhub/aio/operations/__init__.py
azure/mgmt/devhub/aio/operations/_dev_hub_mgmt_client_operations.py
azure/mgmt/devhub/aio/operations/_operations.py
azure/mgmt/devhub/aio/operations/_patch.py
azure/mgmt/devhub/aio/operations/_workflow_operations.py
azure/mgmt/devhub/models/__init__.py
azure/mgmt/devhub/models/_dev_hub_mgmt_client_enums.py
azure/mgmt/devhub/models/_models_py3.py
azure/mgmt/devhub/models/_patch.py
azure/mgmt/devhub/operations/__init__.py
azure/mgmt/devhub/operations/_dev_hub_mgmt_client_operations.py
azure/mgmt/devhub/operations/_operations.py
azure/mgmt/devhub/operations/_patch.py
azure/mgmt/devhub/operations/_workflow_operations.py
azure_mgmt_devhub-1.0.0b1.dist-info/LICENSE
azure_mgmt_devhub-1.0.0b1.dist-info/METADATA
azure_mgmt_devhub-1.0.0b1.dist-info/WHEEL
azure_mgmt_devhub-1.0.0b1.dist-info/top_level.txt
azure_mgmt_devhub-1.0.0b1.dist-info/RECORD
